{
  "@context": "https://linked.art/ns/v1/linked-art.json",
  "id": "https://data.stage.org/festivals/000000000001",
  "type": "Activity",
  "_label": "78e Festival Avignon 2024",
  "classified_as": [
    {
      "id": "http://vocab.getty.edu/page/aat/300386366",
      "type": "Type",
      "_label": "Art festivals"
    }
  ],
  "identified_by": [
    {
      "type": "Name",
      "classified_as": [
        {
          "id": "http://vocab.getty.edu/aat/300404670",
          "type": "Type",
          "_label": "Title"
        }
      ],
      "content": "78e édition du Festival d'Avignon - 2024"
    }
  ],
  "used_specific_object": [
    {
      "id": "https://data.stage.org/programs/000000000001",
      "type": "HumanMadeObject",
      "_label": "Absalon Absalon show programme"
    }
  ],
  "took_place_at": [
    {
      "id": "https://data.stage.org/auth/100000000001",
      "type": "Place",
      "_label": "Avignon, City",
      "classified_as": [
        {
          "id": "http://vocab.getty.edu/page/aat/300008389",
          "type": "Type",
          "_label": "cities"
        }
      ]
    }
  ],
  "timespan": {
    "type": "TimeSpan",
    "begin_of_the_begin": "2024-06-29T00:00:00Z",
    "end_of_the_end": "2024-07-21T00:00:00Z"
  }
}
